flarerun/__init__.py
flarerun/orders.py
tests/__init__.py
tests/test_orders.py
FlareRun-2.0.0.dist-info/LICENSE
FlareRun-2.0.0.dist-info/METADATA
FlareRun-2.0.0.dist-info/WHEEL
FlareRun-2.0.0.dist-info/top_level.txt
FlareRun-2.0.0.dist-info/RECORD
