Metadata-Version: 2.1
Name: FlareRun
Version: 2.0.0
Summary: A comprehensive Python library designed for seamless interaction with FlareRun's trading APIs
Home-page: https://flarerun.online
Author: Aryan Chander
Author-email: aryanchander5@gmail.com
Classifier: Programming Language :: Python :: 3
Classifier: License :: OSI Approved :: MIT License
Classifier: Operating System :: OS Independent
Requires-Python: >=3.6
License-File: LICENSE
Requires-Dist: requests
